databox/__init__.py
databox/databox.py
dwb/__init__.py
dwb/cli.py
miro_dataworkbench-0.1.5.dist-info/METADATA
miro_dataworkbench-0.1.5.dist-info/WHEEL
miro_dataworkbench-0.1.5.dist-info/entry_points.txt
miro_dataworkbench-0.1.5.dist-info/top_level.txt
miro_dataworkbench-0.1.5.dist-info/RECORD
