Metadata-Version: 2.1
Name: miro-dataworkbench
Version: 0.1.5
Requires-Python: >=3.10
Requires-Dist: python-box
Provides-Extra: dev
Requires-Dist: pytest ; extra == 'dev'
Requires-Dist: black ; extra == 'dev'
Requires-Dist: build ; extra == 'dev'
